safari_to_sqlite/__init__.py
safari_to_sqlite/__main__.py
safari_to_sqlite/blacklist.py
safari_to_sqlite/constants.py
safari_to_sqlite/datastore.py
safari_to_sqlite/download.py
safari_to_sqlite/errors.py
safari_to_sqlite/export_from_safari.applescript
safari_to_sqlite/history.py
safari_to_sqlite/more_itertools.py
safari_to_sqlite/safari.py
safari_to_sqlite/turso.py
safari_to_sqlite-0.4.0.dist-info/LICENSE.txt
safari_to_sqlite-0.4.0.dist-info/METADATA
safari_to_sqlite-0.4.0.dist-info/WHEEL
safari_to_sqlite-0.4.0.dist-info/entry_points.txt
safari_to_sqlite-0.4.0.dist-info/top_level.txt
safari_to_sqlite-0.4.0.dist-info/RECORD
