Metadata-Version: 2.1
Name: safari-to-sqlite
Version: 0.4.0
Summary: Save tabs from Safari to a SQLite database. Supports Datasette. Can sync multiple devices with Turso.
Author-email: Harold Martin <Harold.Martin@gmail.com>
License: Apache License
Project-URL: Homepage, https://github.com/hbmartin/safari-to-sqlite
Keywords: browser,datasette,safari,sqlite,tabs
Classifier: Development Status :: 4 - Beta
Classifier: Environment :: Console
Classifier: Framework :: Datasette
Classifier: Intended Audience :: End Users/Desktop
Classifier: Intended Audience :: Science/Research
Classifier: License :: OSI Approved :: Apache Software License
Classifier: Programming Language :: Python :: 3.11
Classifier: Programming Language :: Python :: 3.12
Classifier: Typing :: Typed
Requires-Python: >=3.11
License-File: LICENSE.txt
Requires-Dist: libsql-experimental
Requires-Dist: loguru
Requires-Dist: mureq
Requires-Dist: trafilatura
Provides-Extra: lint
Requires-Dist: black ; extra == 'lint'
Requires-Dist: ruff ; extra == 'lint'
Requires-Dist: pyroma ; extra == 'lint'
Requires-Dist: pytype ; extra == 'lint'
